README.rst
setup.py
demojd/__init__.py
demojd/__main__.py
demojd.egg-info/PKG-INFO
demojd.egg-info/SOURCES.txt
demojd.egg-info/dependency_links.txt
demojd.egg-info/top_level.txt
demojd/data/__init__.py
demojd/data/others.json
demojd/scripts/__init__.py
demojd/scripts/hello.py
demojd/src/__init__.py
demojd/src/general.py
demojd/src/other.py
demojd/src/uncle.py
demojd/src/parents/__init__.py
demojd/src/parents/dad.py
demojd/src/parents/mom.py
demojd/src/parents/kids/__init__.py
demojd/src/parents/kids/boy.py
demojd/src/parents/kids/girl.py