Metadata-Version: 1.0
Name: demojd
Version: 0.44.6
Summary: Hello World demo with tree package structure.
Home-page: UNKNOWN
Author: vipervit
Author-email: vitolg1@gmail.com
License: UNKNOWN
Platform: UNKNOWN
